CHANGELOG.txt
LICENSE
MANIFEST.in
README.md
setup.cfg
setup.py
SKompiler.egg-info/PKG-INFO
SKompiler.egg-info/SOURCES.txt
SKompiler.egg-info/dependency_links.txt
SKompiler.egg-info/requires.txt
SKompiler.egg-info/top_level.txt
SKompiler.egg-info/zip-safe
skompiler/__init__.py
skompiler/api.py
skompiler/ast.py
skompiler/dsl.py
skompiler/fromskast/__init__.py
skompiler/fromskast/_common.py
skompiler/fromskast/excel.py
skompiler/fromskast/pfa.py
skompiler/fromskast/python.py
skompiler/fromskast/sqlalchemy.py
skompiler/fromskast/sympy.py
skompiler/toskast/__init__.py
skompiler/toskast/_common.py
skompiler/toskast/python.py
skompiler/toskast/string.py
skompiler/toskast/sklearn/__init__.py
skompiler/toskast/sklearn/common.py
skompiler/toskast/sklearn/cluster/__init__.py
skompiler/toskast/sklearn/cluster/k_means.py
skompiler/toskast/sklearn/decomposition/__init__.py
skompiler/toskast/sklearn/decomposition/pca.py
skompiler/toskast/sklearn/ensemble/__init__.py
skompiler/toskast/sklearn/ensemble/forest.py
skompiler/toskast/sklearn/ensemble/gradient_boosting.py
skompiler/toskast/sklearn/ensemble/weight_boosting.py
skompiler/toskast/sklearn/linear_model/__init__.py
skompiler/toskast/sklearn/linear_model/base.py
skompiler/toskast/sklearn/linear_model/logistic.py
skompiler/toskast/sklearn/neural_network/__init__.py
skompiler/toskast/sklearn/neural_network/multilayer_perceptron.py
skompiler/toskast/sklearn/preprocessing/__init__.py
skompiler/toskast/sklearn/preprocessing/data.py
skompiler/toskast/sklearn/tree/__init__.py
skompiler/toskast/sklearn/tree/base.py