Metadata-Version: 2.1
Name: SKompiler
Version: 0.6
Summary: Library for compiling trained SKLearn models into abstract expressions suitable for further compilation into executable code in various languages.
Home-page: https://github.com/konstantint/SKompiler
Author: Konstantin Tretyakov
Author-email: konstantin.tretjakov@gmail.com
License: MIT
Keywords: sklearn datascience modelling deployment
Platform: UNKNOWN
Classifier: Development Status :: 3 - Alpha
Classifier: Programming Language :: Python :: 3.5
Classifier: Programming Language :: Python :: 3.6
Classifier: Programming Language :: Python :: 3.7
Classifier: Programming Language :: Python :: 3.8
Classifier: Programming Language :: Python :: 3.9
Classifier: Topic :: Software Development :: Code Generators
Classifier: License :: OSI Approved :: MIT License
Classifier: Intended Audience :: Developers
Classifier: Intended Audience :: Science/Research
Provides-Extra: full
Provides-Extra: test
Provides-Extra: dev
License-File: LICENSE
